.gitignore
.travis.yml
LICENSE
README.md
demo.py
requirements-test.txt
requirements.txt
setup.py
doc/top.png
sumeval/__init__.py
sumeval.egg-info/PKG-INFO
sumeval.egg-info/SOURCES.txt
sumeval.egg-info/dependency_links.txt
sumeval.egg-info/entry_points.txt
sumeval.egg-info/requires.txt
sumeval.egg-info/top_level.txt
sumeval/cli/__init__.py
sumeval/cli/sum_eval.py
sumeval/metrics/__init__.py
sumeval/metrics/bleu.py
sumeval/metrics/rouge.py
sumeval/metrics/lang/__init__.py
sumeval/metrics/lang/base_lang.py
sumeval/metrics/lang/lang_en.py
sumeval/metrics/lang/lang_ja.py
sumeval/metrics/lang/lang_zh.py
sumeval/metrics/lang/data/en/stemming.txt
sumeval/metrics/lang/data/en/stop_words.txt
sumeval/metrics/lang/data/ja/stop_words.txt
sumeval/metrics/lang/data/zh/stop_words.txt
tests/__init__.py
tests/rouge_test_to_json.py
tests/test_be_rouge.py
tests/test_be_rouge_ja.py
tests/test_bleu.py
tests/test_custom_lang.py
tests/test_lang_en.py
tests/test_lang_ja.py
tests/test_lang_zh.py
tests/test_rouge.py
tests/test_rouge_ja.py
tests/test_rouge_zh.py
tests/test_sum_eval.py
tests/data/.gitkeep
tests/data/rouge/ROUGE-test-ja.json
tests/data/rouge/ROUGE-test-zh.json
tests/data/rouge/ROUGE-test.json
tests/data/rouge/verify-spl.json
tests/data/rouge/verify.json