Metadata-Version: 1.1
Name: sumeval
Version: 0.2.2
Summary: Well tested evaluation framework for Text summarization
Home-page: https://github.com/chakki-works/sumeval
Author: icoxfog417
Author-email: icoxfog417@yahoo.co.jp
License: Apache License 2.0
Keywords: text summarization machine learning
Platform: UNKNOWN
Classifier: Programming Language :: Python :: 3.7
Classifier: Programming Language :: Python :: 3.6
